mmg2d/__main__.py
mmg2d/mmg2d_O3
mmg2d/__init__.py
pymmg.libs/libgcc_s-8b50eaaa.so.1
mmgs/mmgs_O3
mmgs/__main__.py
mmgs/__init__.py
general/_version.py
general/__init__.py
pymmg-1.0.0.dist-info/top_level.txt
pymmg-1.0.0.dist-info/METADATA
pymmg-1.0.0.dist-info/WHEEL
pymmg-1.0.0.dist-info/entry_points.txt
mmg3d/__main__.py
mmg3d/mmg3d_O3
mmg3d/__init__.py
pymmg-1.0.0.dist-info/RECORD
