Metadata-Version: 2.1
Name: pymmg
Version: 1.0.0
Summary: Surface and volume mesh and remesh generators based on MMG library
Author: gnikit
License: LGPL-3.0-or-later
Project-URL: Homepage, https://www.mmgtools.org/
Project-URL: Source Code, https://github.com/gnikit/pymmg
Project-URL: Bugs, https://github.com/gnikit/pymmg/issues
Project-URL: Dicsussions, https://forum.mmgtools.org/
Keywords: mesh,remesh,mesh generation,unstructured
Classifier: Development Status :: 5 - Production/Stable
Classifier: Intended Audience :: Science/Research
Classifier: License :: OSI Approved :: MIT License
Classifier: Operating System :: OS Independent
Classifier: Programming Language :: Python
Classifier: Programming Language :: Python :: 3
Classifier: Programming Language :: Python :: 3.7
Classifier: Programming Language :: Python :: 3.8
Classifier: Programming Language :: Python :: 3.9
Classifier: Programming Language :: Python :: 3.10
Classifier: Programming Language :: Python :: 3.11
Classifier: Topic :: Scientific/Engineering
Classifier: Topic :: Utilities
Requires-Python: >=3.7
Requires-Dist: meshio
Provides-Extra: all
Requires-Dist: meshio[all] ; extra == 'all'
